witnesschain/__init__.py
witnesschain/constants.py
witnesschain/datatypes.py
witnesschain/exceptions.py
witnesschain/infinitywatch.py
witnesschain-0.1.9.dist-info/METADATA
witnesschain-0.1.9.dist-info/WHEEL
witnesschain-0.1.9.dist-info/entry_points.txt
witnesschain-0.1.9.dist-info/RECORD
