Metadata-Version: 2.4
Name: witnesschain
Version: 0.1.9
Summary: tools for accessing witnesschain's infinitywatch network
Author-email: Aswin <43544673+Aswin-ElMagnifico@users.noreply.github.com>, witnesschain <developers@witnesschain.com>
Requires-Python: >=3.10.17
Requires-Dist: aiohttp>=3.12.14
